odoo/addons/l10n_fr_account_invoice_import_facturx/README.rst
odoo/addons/l10n_fr_account_invoice_import_facturx/__init__.py
odoo/addons/l10n_fr_account_invoice_import_facturx/__manifest__.py
odoo/addons/l10n_fr_account_invoice_import_facturx/i18n/fr.po
odoo/addons/l10n_fr_account_invoice_import_facturx/i18n/l10n_fr_account_invoice_import_factur-x.pot
odoo/addons/l10n_fr_account_invoice_import_facturx/i18n/l10n_fr_account_invoice_import_facturx.pot
odoo/addons/l10n_fr_account_invoice_import_facturx/models/__init__.py
odoo/addons/l10n_fr_account_invoice_import_facturx/models/res_partner.py
odoo/addons/l10n_fr_account_invoice_import_facturx/readme/CONTRIBUTORS.rst
odoo/addons/l10n_fr_account_invoice_import_facturx/readme/DESCRIPTION.rst
odoo/addons/l10n_fr_account_invoice_import_facturx/static/description/icon.png
odoo/addons/l10n_fr_account_invoice_import_facturx/static/description/index.html
odoo/addons/l10n_fr_account_invoice_import_facturx/wizard/__init__.py
odoo/addons/l10n_fr_account_invoice_import_facturx/wizard/account_invoice_import.py
odoo_addon_l10n_fr_account_invoice_import_facturx-16.0.1.2.0.dist-info/METADATA
odoo_addon_l10n_fr_account_invoice_import_facturx-16.0.1.2.0.dist-info/WHEEL
odoo_addon_l10n_fr_account_invoice_import_facturx-16.0.1.2.0.dist-info/top_level.txt
odoo_addon_l10n_fr_account_invoice_import_facturx-16.0.1.2.0.dist-info/RECORD
