Metadata-Version: 2.1
Name: odoo-addon-l10n_fr_account_invoice_import_facturx
Version: 16.0.1.2.0
Summary: France-specific module to import Factur-X invoices
Home-page: https://github.com/OCA/l10n-france
Author: Akretion,Odoo Community Association (OCA)
Author-email: support@odoo-community.org
License: AGPL-3
Classifier: Programming Language :: Python
Classifier: Framework :: Odoo
Classifier: Framework :: Odoo :: 16.0
Classifier: License :: OSI Approved :: GNU Affero General Public License v3
Requires-Python: >=3.10
Requires-Dist: odoo-addon-account-invoice-import-facturx<16.1dev,>=16.0dev
Requires-Dist: odoo-addon-l10n-fr-business-document-import<16.1dev,>=16.0dev
Requires-Dist: odoo<16.1dev,>=16.0a
